cansii/__init__.py
cansii/styles.py
cansii-1.2.dist-info/LICENSE
cansii-1.2.dist-info/METADATA
cansii-1.2.dist-info/WHEEL
cansii-1.2.dist-info/top_level.txt
cansii-1.2.dist-info/RECORD
