Metadata-Version: 2.1
Name: cansii
Version: 1.2
Summary: A Python library for terminal text colorization using ANSI escape codes.
Home-page: https://github.com/JuanPerdomo00/CAnsii
Author: Jakepys Perdomo
Author-email: perdomojuan187@gmail.com
License: GPL-3.0
Classifier: Development Status :: 3 - Alpha
Classifier: Intended Audience :: Developers
Classifier: License :: OSI Approved :: GNU General Public License v3 (GPLv3)
Classifier: Programming Language :: Python :: 3
Classifier: Programming Language :: Python :: 3.9
Classifier: Programming Language :: Python :: 3.8
Classifier: Programming Language :: Python :: 3.7
License-File: LICENSE
